mvcomp.py
plotting.py
utils.py
MVComp-0.9.4.dist-info/LICENSE
MVComp-0.9.4.dist-info/METADATA
MVComp-0.9.4.dist-info/WHEEL
MVComp-0.9.4.dist-info/top_level.txt
MVComp-0.9.4.dist-info/RECORD
